Lab2/mux.v
// output is A (when control == 0) or B (when control == 1)
module mux2(out, A, B, control);
    output out;
    input  A, B;
    input  control;
    wire   wA, wB, not_control;

    not n1(not_control, control);
    and a1(wA, A, not_control);
    and a2(wB, B, control);
    or  o1(out, wA, wB);
endmodule // mux2

// output is A (when control == 00) or B (when control == 01) or
//           C (when control == 10) or D (when control == 11)
module mux4(out, A, B, C, D, control);
    output      out;
    input       A, B, C, D;
    input [1:0] control;
wire   wA,wB,wC,wD,not_control1,not_control0;

not n1(not_control1,control[1]);
not n0(not_control0,control[0]);

and a1(wA,A,not_control1,not_control0);
and a2(wB,B,not_control1,control[0]);
and a3(wC,C,control[1],not_control0);
and a4(wD,D,control[1],control[0]);

or o1(out,wA,wB,wC,wD);
endmodule // mux4

Lab2/logicunit.v
// 00 -> AND, 01 -> OR, 10 -> NOR, 11 -> XOR
module logicunit(out, A, B, control);
    output      out;
    input       A, B;
    input [1:0] control;
    wire   w1,w2,w3,w4,wA,wB,wC,wD,not_control1,not_control0;

not n1(not_control1,control[1]);
not n0(not_control0,control[0]);

//check 00 and
and a1(wA,not_control1,not_control0, w1);
assign w1 = A & B;

//check 01 or
and a2(wB,not_control1,control[0], w2);
assign w2 = A | B;

//check 10 nor
and a3(wC,control[1],not_control0, w3);
assign w3 = A ~| B;

//check 11 xor
and a4(wD,control[1],control[0], w4);
assign w4 = A ^ B;

or o1(out,wA,wB,wC,wD);

endmodule // logicunit

Lab2/alu1.v
module full_adder(sum, cout, a, b, cin);
    output sum, cout;
    input  a, b, cin;
    wire   partial_s, partial_c1, partial_c2;

    xor x0(partial_s, a, b);
    xor x1(sum, partial_s, cin);
    and a0(partial_c1, a, b);
    and a1(partial_c2, partial_s, cin);
    or  o1(cout, partial_c1, partial_c2);
endmodule // full_adder

`define ALU_ADD    3'h2
`define ALU_SUB    3'h3
`define ALU_AND    3'h4
`define ALU_OR     3'h5
`define ALU_NOR    3'h6
`define ALU_XOR    3'h7

// 01x -> arithmetic, 1xx -> logic
module alu1(out, carryout, A, B, carryin, control);
    output      out, carryout;
    input       A, B, carryin;
    input [2:0] control;

    // add code here!!!
    wire xor_out, sum, logic_out;
    xor xorgate(xor_out,control[0], B);
    full_adder add(sum, carryout, A, xor_out, carryin);
    logicunit logi(logic_out, A, B, control[1:0]);
    mux2 mux(out, sum, logic_out, control[2]);


endmodule // alu1

Lab2/alu1_tb.v
module alu1_test;
    // exhaustively test your 1-bit ALU implementation by adapting mux4_tb.v

    // cycle through all combinations of A, B, C, D every 16 time units
    reg A = 0;
    always #1 A = !A;
    reg B = 0;
    always #2 B = !B;
    reg carryin = 0;
    always #4 carryin = !carryin;

    reg [2:0] control = 0;

    initial begin
        $dumpfile("alu1.vcd");
        $dumpvars(0, alu1_test);

        // control is initially 0
        # 8 control = 2; // wait 16 time units (why 16?) and then set it to 1
        # 8 control = 3; // wait 16 time units and then set it to 2
        # 8 control = 4; // wait 16 time units and then set it to 3
        # 8 control = 5; // wait 16 time units (why 16?) and then set it to 1
        # 8 control = 6; // wait 16 time units and then set it to 2
        # 8 control = 7; // wait 16 time units and then set it to 3
        # 8 $finish; // wait 16 time units and then end the simulation
        // # 16 control = 1; // wait 16 time units (why 16?) and then set it to 1
        // # 16 control = 2; // wait 16 time units and then set it to 2
        // # 16 control = 3; // wait 16 time units and then set it to 3
        // # 16 $finish; // wait 16 time units and then end the simulation
    end

    wire out, carryout;
    alu1 a1(out, carryout, A, B, carryin, control);

    // you really should be using gtkwave instead

    // initial begin
    //     $display("A B C D s o");
    //     $monitor("%d %d %d %d %d %d (at time %t)", A, B, C, D, control, out, $time);
    // end

endmodule

Lab2/alu1.vcd
$date
	Sat Sep  7 15:06:00 2019
$end
$version
	Icarus Verilog
$end
$timescale
	1s
$end
$scope module alu1_test $end
$var wire 1 ! out $end
$var wire 1 " carryout $end
$var reg 1 # A $end
$var reg 1 $ B $end
$var reg 1 % carryin $end
$var reg 3 & control [2:0] $end
$scope module a1 $end
$var wire 1 # A $end
$var wire 1 $ B $end
$var wire 1 % carryin $end
$var wire 3 ' control [2:0] $end
$var wire 1 ( xor_out $end
$var wire 1 ) sum $end
$var wire 1 ! out $end
$var wire 1 * logic_out $end
$var wire 1 " carryout $end
$scope module add $end
$var wire 1 # a $end
$var wire 1 ( b $end
$var wire 1 % cin $end
$var wire 1 " cout $end
$var wire 1 + partial_c1 $end
$var wire 1 , partial_c2 $end
$var wire 1 - partial_s $end
$var wire 1 ) sum $end
$upscope $end
$scope module logi $end
$var wire 1 # A $end
$var wire 1 $ B $end
$var wire 2 . control [1:0] $end
$var wire 1 / not_control0 $end
$var wire 1 0 not_control1 $end
$var wire 1 * out $end
$var wire 1 1 w1 $end
$var wire 1 2 w2 $end
$var wire 1 3 w3 $end
$var wire 1 4 w4 $end
$var wire 1 5 wA $end
$var wire 1 6 wB $end
$var wire 1 7 wC $end
$var wire 1 8 wD $end
$upscope $end
$scope module mux $end
$var wire 1 ) A $end
$var wire 1 * B $end
$var wire 1 9 control $end
$var wire 1 : not_control $end
$var wire 1 ! out $end
$var wire 1 ; wA $end
$var wire 1 < wB $end
$upscope $end
$upscope $end
$upscope $end
$enddefinitions $end
#0
$dumpvars
0<
0;
1:
09
08
07
06
05
04
13
02
01
10
1/
b0 .
0-
0,
0+
0*
0)
0(
b0 '
b0 &
0%
0$
0#
0"
0!
$end
#1
1!
1;
1)
1-
12
03
14
1#
#2
1(
0#
1$
#3
0!
0;
1*
0)
1"
15
0-
1+
11
04
1#
#4
0*
1!
0"
05
1;
0+
0(
01
02
13
1)
0#
0$
1%
#5
0!
0;
1"
0)
1,
1-
12
03
14
1#
#6
1(
0#
1$
#7
1!
1;
1*
1)
0,
15
0-
1+
11
04
1#
#8
0!
00
0"
05
17
0;
0+
0(
01
02
13
0)
b10 .
0#
0$
0%
b10 &
b10 '
#9
1!
1;
0*
1)
07
1-
12
03
14
1#
#10
1(
0#
1$
#11
0!
0;
0)
1"
0-
1+
11
04
1#
#12
1*
1!
0"
17
1;
0+
0(
01
02
13
1)
0#
0$
1%
#13
0!
0;
1"
0*
0)
1,
07
1-
12
03
14
1#
#14
1(
0#
1$
#15
1!
1;
1)
0,
0-
1+
11
04
1#
#16
0*
1!
0/
0"
07
1;
1-
0+
01
02
13
1)
b11 .
0#
0$
0%
b11 &
b11 '
#17
0!
0;
1*
0)
1"
18
0-
1+
12
03
14
1#
#18
0"
0+
0(
0#
1$
#19
1!
1;
0*
1)
08
1-
11
04
1#
#20
0!
0;
1"
1(
01
02
13
0)
1,
0#
0$
1%
#21
1!
1;
1*
1)
0,
18
0-
1+
12
03
14
1#
#22
0"
0+
0(
0#
1$
#23
0!
0;
1"
0*
0)
1,
08
1-
11
04
1#
#24
10
1/
0"
0:
0-
01
02
13
0)
0,
b0 .
19
0#
0$
0%
b100 &
b100 '
#25
1)
1-
12
03
14
1#
#26
1(
0#
1$
#27
1!
1<
1*
0)
1"
15
0-
1+
11
04
1#
#28
0!
0<
0*
0"
05
0+
0(
01
02
13
1)
0#
0$
1%
#29
1"
0)
1,
1-
12
03
14
1#
#30
1(
0#
1$
#31
1!
1<
1*
1)
0,
15
0-
1+
11
04
1#
#32
0!
0<
0*
0/
0"
05
1-
0+
01
02
13
1)
b1 .
0#
0$
0%
b101 &
b101 '
#33
1!
1<
1*
0)
1"
16
0-
1+
12
03
14
1#
#34
0"
0+
0(
0#
1$
#35
1)
1-
11
04
1#
#36
0!
0<
0*
06
1"
1(
01
02
13
0)
1,
0#
0$
1%
#37
1!
1<
1*
1)
0,
16
0-
1+
12
03
14
1#
#38
0"
0+
0(
0#
1$
#39
1"
0)
1,
1-
11
04
1#
#40
1!
1<
17
1*
00
1/
06
0"
0-
01
02
13
0)
0,
b10 .
0#
0$
0%
b110 &
b110 '
#41
0!
0<
0*
1)
07
1-
12
03
14
1#
#42
1(
0#
1$
#43
0)
1"
0-
1+
11
04
1#
#44
1!
1<
1*
0"
17
0+
0(
01
02
13
1)
0#
0$
1%
#45
0!
0<
1"
0*
0)
1,
07
1-
12
03
14
1#
#46
1(
0#
1$
#47
1)
0,
0-
1+
11
04
1#
#48
0!
0<
0*
0/
0"
07
1-
0+
01
02
13
1)
b11 .
0#
0$
0%
b111 &
b111 '
#49
1!
1<
1*
0)
1"
18
0-
1+
12
03
14
1#
#50
0"
0+
0(
0#
1$
#51
0!
0<
0*
1)
08
1-
11
04
1#
#52
1"
1(
01
02
13
0)
1,
0#
0$
1%
#53
1!
1<
1*
1)
0,
18
0-
1+
12
03
14
1#
#54
0"
0+
0(
0#
1$
#55
0!
0<
1"
0*
0)
1,
08
1-
11
04
1#
#56
0"
1(
01
02
13
1)
0,
0#
0$
0%
