Lab2/logicunit.v
// 00 -> AND, 01 -> OR, 10 -> NOR, 11 -> XOR
module logicunit(out, A, B, control);
    output      out;
    input       A, B;
    input [1:0] control;
    wire   w1,w2,w3,w4,wA,wB,wC,wD,not_control1,not_control0;

not n1(not_control1,control[1]);
not n0(not_control0,control[0]);

//check 00 and
and a1(wA,not_control1,not_control0, w1);
assign w1 = A & B;

//check 01 or
and a2(wB,not_control1,control[0], w2);
assign w2 = A | B;

//check 10 nor
and a3(wC,control[1],not_control0, w3);
assign w3 = A ~| B;

//check 11 xor
and a4(wD,control[1],control[0], w4);
assign w4 = A ^ B;

or o1(out,wA,wB,wC,wD);

endmodule // logicunit

Lab2/logicunit_tb.v
module logicunit_test;
    // exhaustively test your logic unit implementation by adapting mux4_tb.v
    reg A = 0;
always #1 A = !A;
reg B = 0;
always #2 B = !B;

reg [1:0] control = 0;

initial begin
$dumpfile("logicunit.vcd");
$dumpvars(0, logicunit_test);

// control is initially 0
# 16 control = 1; // wait 16 time units (why 16?) and then set it to 1
# 16 control = 2; // wait 16 time units and then set it to 2
# 16 control = 3; // wait 16 time units and then set it to 3
# 16 $finish; // wait 16 time units and then end the simulation
end

wire out;
logicunit l1(out, A, B, control);

initial begin
$display("A B s o");
$monitor("%d %d %d %d (at time %t)", A, B, control, out, $time);
end
endmodule // logicunit_test

Lab2/logicunit.vcd
$date
	Wed Sep  4 22:43:31 2019
$end
$version
	Icarus Verilog
$end
$timescale
	1s
$end
$scope module logicunit_test $end
$var wire 1 ! out $end
$var reg 1 " A $end
$var reg 1 # B $end
$var reg 2 $ control [1:0] $end
$scope module l1 $end
$var wire 1 " A $end
$var wire 1 # B $end
$var wire 2 % control [1:0] $end
$var wire 1 & not_control0 $end
$var wire 1 ' not_control1 $end
$var wire 1 ! out $end
$var wire 1 ( w1 $end
$var wire 1 ) w2 $end
$var wire 1 * w3 $end
$var wire 1 + w4 $end
$var wire 1 , wA $end
$var wire 1 - wB $end
$var wire 1 . wC $end
$var wire 1 / wD $end
$upscope $end
$upscope $end
$enddefinitions $end
#0
$dumpvars
0/
0.
0-
0,
0+
1*
0)
0(
1'
1&
b0 %
b0 $
0#
0"
0!
$end
#1
1)
0*
1+
1"
#2
0"
1#
#3
1!
1,
1(
0+
1"
#4
0!
0,
0(
0)
1*
0"
0#
#5
1)
0*
1+
1"
#6
0"
1#
#7
1!
1,
1(
0+
1"
#8
0!
0,
0(
0)
1*
0"
0#
#9
1)
0*
1+
1"
#10
0"
1#
#11
1!
1,
1(
0+
1"
#12
0!
0,
0(
0)
1*
0"
0#
#13
1)
0*
1+
1"
#14
0"
1#
#15
1!
1,
1(
0+
1"
#16
0!
0,
0&
0(
0)
1*
0"
0#
b1 $
b1 %
#17
1!
1-
1)
0*
1+
1"
#18
0"
1#
#19
1(
0+
1"
#20
0!
0-
0(
0)
1*
0"
0#
#21
1!
1-
1)
0*
1+
1"
#22
0"
1#
#23
1(
0+
1"
#24
0!
0-
0(
0)
1*
0"
0#
#25
1!
1-
1)
0*
1+
1"
#26
0"
1#
#27
1(
0+
1"
#28
0!
0-
0(
0)
1*
0"
0#
#29
1!
1-
1)
0*
1+
1"
#30
0"
1#
#31
1(
0+
1"
#32
1.
1!
0'
1&
0-
0(
0)
1*
0"
0#
b10 $
b10 %
#33
0!
0.
1)
0*
1+
1"
#34
0"
1#
#35
1(
0+
1"
#36
1!
1.
0(
0)
1*
0"
0#
#37
0!
0.
1)
0*
1+
1"
#38
0"
1#
#39
1(
0+
1"
#40
1!
1.
0(
0)
1*
0"
0#
#41
0!
0.
1)
0*
1+
1"
#42
0"
1#
#43
1(
0+
1"
#44
1!
1.
0(
0)
1*
0"
0#
#45
0!
0.
1)
0*
1+
1"
#46
0"
1#
#47
1(
0+
1"
#48
0&
0(
0)
1*
0"
0#
b11 $
b11 %
#49
1!
1/
1)
0*
1+
1"
#50
0"
1#
#51
0!
0/
1(
0+
1"
#52
0(
0)
1*
0"
0#
#53
1!
1/
1)
0*
1+
1"
#54
0"
1#
#55
0!
0/
1(
0+
1"
#56
0(
0)
1*
0"
0#
#57
1!
1/
1)
0*
1+
1"
#58
0"
1#
#59
0!
0/
1(
0+
1"
#60
0(
0)
1*
0"
0#
#61
1!
1/
1)
0*
1+
1"
#62
0"
1#
#63
0!
0/
1(
0+
1"
#64
0(
0)
1*
0"
0#
